README.txt
setup.py
DrQueue/__init__.py
DrQueue/client.py
DrQueue/computer.py
DrQueue/computer_pool.py
DrQueue/engine_helpers.py
DrQueue/job.py
DrQueueIPython.egg-info/PKG-INFO
DrQueueIPython.egg-info/SOURCES.txt
DrQueueIPython.egg-info/dependency_links.txt
DrQueueIPython.egg-info/requires.txt
DrQueueIPython.egg-info/top_level.txt
bin/control_computer.py
bin/control_job.py
bin/drqueue_master.py
bin/drqueue_slave.py
bin/list_computers.py
bin/list_jobs.py
bin/send_job.py