Metadata-Version: 1.0
Name: DrQueueIPython
Version: 0.0.1
Summary: This is a port of DrQueue to Python. IPython is used for network communication and task management.
Home-page: https://ssl.drqueue.org/redmine/projects/drqueueipython
Author: Andreas Schroeder
Author-email: andreas@drqueue.org
License: GPLv3
Keywords: render renderfarm management drqueue
Platform: UNKNOWN
Classifier: Development Status :: 3 - Alpha
Classifier: Topic :: Utilities
Classifier: License :: OSI Approved :: GNU General Public License (GPL)
